{
    "conversation_patterns": [
        {
            "pattern": "Integration of AI in facilitation",
            "evidence": "The conversation discusses the technical setup and facilitation processes for the event, emphasizing the role of AI in enhancing dialogues.",
            "timestamps": [
                "00:00:00 - 00:00:15",
                "00:02:45 - 00:03:00",
                "00:04:00 - 00:04:15",
                "00:06:00 - 00:06:15"
            ]
        },
        {
            "pattern": "Addressing fears and concerns",
            "evidence": "Participants acknowledge and discuss fears related to AI development and its implications for organizations.",
            "timestamps": [
                "00:04:15 - 00:04:30",
                "00:04:45 - 00:05:00"
            ]
        }
    ],
    "organizational_needs": [
        {
            "need": "Technical support for AI integration",
            "urgency_score": 8.0,
            "evidence": "The team seeks clarity on how to assist if technical issues arise during the workshop."
        },
        {
            "need": "Facilitated generative dialogues",
            "urgency_score": 7.0,
            "evidence": "The agenda includes structured dialogue rounds to foster exploration and innovation among participants."
        }
    ],
    "emerging_trajectories": [
        {
            "trajectory": "Increased reliance on AI for meeting facilitation",
            "implications": "Organizations may experience enhanced dialogue quality and efficiency in decision-making processes."
        }
    ],
    "leverage_points": [
        {
            "point": "Utilizing AI for real-time feedback",
            "potential_impact": "This can improve dialogue depth and help identify blind spots during discussions."
        }
    ],
    "latent_insights": [
        {
            "insight": "Balancing technology and human interaction is crucial",
            "transformation_potential": "Enhancing the effectiveness of AI implementations in organizational settings."
        }
    ],
    "weighted_conclusions": [
        {
            "weight": 0.9,
            "category": "High Priority",
            "conclusion": "Addressing technical concerns early on is essential for a successful integration of AI in workshops.",
            "evidence": "Multiple instances of discussion on the need for support and clarity regarding technical setups."
        }
    ]
}